cryptogym/__init__.py
cryptogym/env.py
cryptogym-0.0.14.dist-info/LICENSE
cryptogym-0.0.14.dist-info/METADATA
cryptogym-0.0.14.dist-info/WHEEL
cryptogym-0.0.14.dist-info/top_level.txt
cryptogym-0.0.14.dist-info/RECORD
